LICENCE
MANIFEST.in
README.md
setup.cfg
setup.py
ruruki/VERSION
ruruki/__init__.py
ruruki/entities.py
ruruki/graphs.py
ruruki/interfaces.py
ruruki/locks.py
ruruki.egg-info/PKG-INFO
ruruki.egg-info/SOURCES.txt
ruruki.egg-info/dependency_links.txt
ruruki.egg-info/requires.txt
ruruki.egg-info/top_level.txt
ruruki/algorithms/__init__.py
ruruki/algorithms/tests/__init__.py
ruruki/parsers/__init__.py
ruruki/parsers/cypher_parser.py
ruruki/parsers/tests/__init__.py
ruruki/parsers/tests/test_cypher_parser.py
ruruki/test_utils/__init__.py
ruruki/test_utils/base.py
ruruki/test_utils/helpers.py
ruruki/test_utils/scrape.py
ruruki/test_utils/tutorial_books_demo.py
ruruki/tests/__init__.py
ruruki/tests/test_database.py
ruruki/tests/test_entities.py
ruruki/tests/test_entities_sets.py
ruruki/tests/test_locks.py