Metadata-Version: 1.1
Name: ruruki
Version: 1.4.2
Summary: Ruruki is a lightweight in-memory graph database which is ideal if you need a temporary graph database, or just doing a proof of concept and need a fast and reliable graph database.
Home-page: https://github.com/optiver/ruruki
Author: Jenda Mudron
Author-email: Jenda.Mudron@optiver.com.au
License: UNKNOWN
Keywords: graph db memory database in-memory snail extraction tool POC proof concept temporary lightweight
Platform: UNKNOWN
Classifier: Development Status :: 4 - Beta
Classifier: License :: OSI Approved :: Apache Software License
Classifier: Operating System :: MacOS
Classifier: Operating System :: POSIX :: BSD
Classifier: Operating System :: POSIX :: Linux
Classifier: Operating System :: Unix
Classifier: Intended Audience :: Developers
Classifier: Intended Audience :: Information Technology
Classifier: Programming Language :: Python :: 2.7
Classifier: Programming Language :: Python :: 3.3
Classifier: Programming Language :: Python :: 3.4
Classifier: Programming Language :: Python :: 3.5
Classifier: Topic :: Database :: Database Engines/Servers
Classifier: Topic :: Software Development :: Libraries
